llama_index/observability/otel/__init__.py
llama_index/observability/otel/base.py
llama_index/observability/otel/utils.py
llama_index_observability_otel-0.2.1.dist-info/METADATA
llama_index_observability_otel-0.2.1.dist-info/WHEEL
llama_index_observability_otel-0.2.1.dist-info/licenses/LICENSE
llama_index_observability_otel-0.2.1.dist-info/RECORD
