Metadata-Version: 2.4
Name: llama-index-observability-otel
Version: 0.2.1
Summary: llama-index observability integration with OpenTelemetry
Author-email: Clelia Astra Bertelli <clelia@runllama.ai>
License-Expression: MIT
License-File: LICENSE
Requires-Python: <4.0,>=3.9
Requires-Dist: llama-index-core<0.15,>=0.13.0
Requires-Dist: opentelemetry-api<2,>=1.33.0
Requires-Dist: opentelemetry-sdk<2,>=1.33.0
Requires-Dist: opentelemetry-semantic-conventions<1,>=0.54b0
Requires-Dist: termcolor<4,>=3.1.0
